README.rst
setup.py
vdf2json/__init__.py
vdf2json/cli.py
vdf2json.egg-info/PKG-INFO
vdf2json.egg-info/SOURCES.txt
vdf2json.egg-info/dependency_links.txt
vdf2json.egg-info/entry_points.txt
vdf2json.egg-info/not-zip-safe
vdf2json.egg-info/requires.txt
vdf2json.egg-info/top_level.txt